comickaze/Comickaze.py
comickaze/Converter.py
comickaze/Downloader.py
comickaze/__init__.py
comickaze/exceptions.py
comickaze/util.py
comickaze/objects/Chapter.py
comickaze/objects/Comic.py
comickaze/objects/Suggestion.py
comickaze/objects/__init__.py
Comickaze-2.0.0.dist-info/LICENSE
Comickaze-2.0.0.dist-info/METADATA
Comickaze-2.0.0.dist-info/WHEEL
Comickaze-2.0.0.dist-info/entry_points.txt
Comickaze-2.0.0.dist-info/top_level.txt
Comickaze-2.0.0.dist-info/RECORD
