Metadata-Version: 2.1
Name: Comickaze
Version: 2.0.0
Summary: A package to search and download comics on ReadComicsOnline.ru
Home-page: https://github.com/Chr1st-oo/comickaze
Author: Aaron Gonzales
Author-email: aaroncgonzales.dev@gmail.com
License: MIT
Platform: UNKNOWN
Classifier: Programming Language :: Python :: 3
Classifier: License :: OSI Approved :: MIT License
Classifier: Operating System :: OS Independent
Requires-Dist: requests
Requires-Dist: bs4
Requires-Dist: coloredlogs
Requires-Dist: colorama
Requires-Dist: progress
Requires-Dist: img2pdf
Requires-Dist: Click
Requires-Dist: pyinquirer
